setup.py
pyoauth2/__init__.py
pyoauth2/client.py
pyoauth2.egg-info/PKG-INFO
pyoauth2.egg-info/SOURCES.txt
pyoauth2.egg-info/dependency_links.txt
pyoauth2.egg-info/requires.txt
pyoauth2.egg-info/top_level.txt
test/test_client.py