Metadata-Version: 1.0
Name: pyoauth2
Version: 0.0.3
Summary: Simple OAuth 2.0 client library
Home-page: https://github.com/ymotongpoo/pyoauth2
Author: Yoshifumi YAMAGUCHI
Author-email: ymotongpoo at gmall.com
License: New BSD
Platform: UNKNOWN
